open2d/__init__.py
open2d/imagealgorithman.cp38-win_amd64.pyd
open2d-5.7.15.dist-info/LICENSE
open2d-5.7.15.dist-info/METADATA
open2d-5.7.15.dist-info/WHEEL
open2d-5.7.15.dist-info/top_level.txt
open2d-5.7.15.dist-info/RECORD
