Metadata-Version: 2.1
Name: open2d
Version: 5.7.15
Summary: This is a collection of digital image algorithms.
Author: AlMan
Classifier: Programming Language :: Python
Classifier: Programming Language :: Cython
Classifier: License :: OSI Approved :: MIT License
Requires-Python: >=3.8
License-File: LICENSE
